{
    "ABNAction": "CreateNewAccount",
    "ABNDetails": {
        "EnterABN": {
            "ABN": "14074218956",
            "ABNCalculation": 6,
            "ABNRemainder": "6",
            "ABNRemainderMessage": null,
            "CustomLWC1": null
        },
        "Messaging1": null,
        "RecordTypeName": "Management Company"
    },
    "ABNDuplicateCheck": {
        "CountABN": 0,
        "CountMCABN": 0
    },
    "ABNValidated": "Ok",
    "ACNErrorCheck": "OK",
    "ACOPostalAddresses": null,
    "ACO_Candidates": null,
    "AOABNDuplicateCheckError": "Ok",
    "APABNDuplicateCheckError": "Ok",
    "ARBNErrorCheck": "OK",
    "ARBNIncIdErrorCheck": "OK",
    "Account": {
        "ABN": "49096776895"
    },
    "AccountPointOfContact": {
        "PointOfContact": {
            "ContactPOCInformation-Block": {
                "ContactBirthdate": "1/5/1997",
                "ContactBirthdateText": "1/5/1997",
                "ContactBirthdate_LoadFormat": "1997-05-01",
                "ContactFirstName": "Sarah",
                "ContactId": "0039r000001k5CEAAY",
                "ContactIntegrationID": "00083",
                "ContactLastName": "SDO KP (workflow test)",
                "ContactName": "Sarah SDO KP (workflow test)",
                "ContactPOCInformation": "Sarah SDO KP (workflow test) 01/May/1997",
                "ContactPassportNumber": "3097",
                "ContactSearchString": "Sarah SDO KP (workflow test) 01/May/1997"
            },
            "DateComparisonFormula_POC": "Good",
            "Messaging2": null,
            "Phone_POC": "0455335555",
            "PositionTitle_POC": "tytutyu",
            "Role_POC": "Service Contact",
            "StartDate_POC": "2022-12-05T13:00:00.000Z"
        }
    },
    "Action": "CreateNewAccount",
    "AddressRecordType": "Physical Address",
    "AddressRecordTypeOverride": "Physical Address",
    "AgedCareOrganisation": null,
    "CHSPABNDuplicateCheckError": "Ok",
    "DisplayABNValidation": {
        "ABNBranch": "001",
        "GREFlag": "N",
        "GREFlagUpdate": null,
        "GREResult": "N",
        "UpdateGRE": "No"
    },
    "DuplicateCheck": {
        "ACOName": 0
    },
    "FinalACOCareOf": "",
    "FinalACOPostalAddress": "NotApplicable",
    "FinalCareOf": "",
    "FinalPOBox": "NotApplicable",
    "FinalPhysicalAddress": "TEST, LAKE EYRE, SA",
    "FinalPostalAddress": "TEST, LAKE EYRE, SA",
    "GovErrorCheck": "OK",
    "HasMagicKey": "OK",
    "IANErrorCheck": "OK",
    "ICNErrorCheck": "OK",
    "LinkToACO": null,
    "LocationRecordType": "Account Address",
    "LocationRecordTypeOverride": "Account Address",
    "MCABNDuplicateCheckError": "Ok",
    "ManagementCompany": {
        "FindAP": {
            "ApprovedProviderInformation-Block": {
                "ACO_ARBN": "000000000",
                "ACO_Id": "0019r000003F0fYAAS",
                "ACO_IncorporatedUnder": "Associations Incorporation Act 1981 (VIC)",
                "ACO_IncorporationID": "123456",
                "ACO_IncorporationIDType": "IAN",
                "ACO_IncorporationStatus": "Registered",
                "ACO_IncorporationStatusDate": "4/5/2022",
                "ACO_IncorporationStatusDate_LoadFormat": "2022-05-04",
                "ACO_IncorporationType": "Incorporated Association",
                "ACO_Name": "Logan's ACO",
                "ApprovedProviderABN": "49096776895",
                "ApprovedProviderAccountNumber": "PRV-87203",
                "ApprovedProviderId": "0019r000004B9vJAAS",
                "ApprovedProviderInformation": "Logan's AP (ACQSC SU) - PRV-87203",
                "ApprovedProviderName": "Logan's AP (ACQSC SU)",
                "ApprovedProviderOrganisationType": "Religious",
                "ApprovedProviderPurpose": "Not for Profit",
                "ApprovedProviderSearchString": "Logan's AP (ACQSC SU) - PRV-87203"
            }
        },
        "MCDetail": {
            "IsApprovedProvider": "Yes",
            "ManagementCompanyName": "test abnid",
            "NameEffectiveDate": "2022-12-08"
        }
    },
    "ManagementCompanyContactInformation": {
        "MCContactDetails": {
            "Email_CON": "tettttt@tetstt.com",
            "EnterNameOfBranch_CON": null,
            "OrganisationContactType_CON": "General Enquiry",
            "Phone_CON": "0455336666"
        }
    },
    "NATSIFACABNDuplicateCheckError": "Ok",
    "New Summary": {
    },
    "Origin": "OmniScript",
    "OtherErrorCheck": "OK",
    "PhysicalAddresses": {
        "Address": {
            "AddressEntry": false,
            "BuildingName_Physical": null,
            "BuildingRadio_Physical": null,
            "ConfirmedAddress": true,
            "Country_Physical": "Australia",
            "Disp_Action": "CreateNewAccount",
            "Disp_AddressRecType": "Physical Address",
            "Disp_AddressType": "",
            "Disp_CurrentServiceId": "",
            "Disp_ServiceAddressId": null,
            "EffectiveDate1": "2022-12-08",
            "EffectiveDate2": null,
            "EffectiveDateFormula": "2022-12-08",
            "HelpText1": true,
            "HelpText2": true,
            "IsPostcodeValid": "BAD",
            "LevelFloorRadio_Physical": null,
            "LevelFloor_Physical": null,
            "LevelFloor_Physical_UPPER": "",
            "LotStreetRadio_Physical": null,
            "PhysicalAddress-Block": {
                "PhysicalAddress": "TEST, LAKE EYRE, SA",
                "address": "TEST, LAKE EYRE, SA",
                "is_collection": false,
                "magic_key": "dHA9MCNsb2M9NzE0NjgwI2xuZz0wI2xicz0xMDk6NDg4OTkxNTc=",
                "success_TypeAhead": "OK"
            },
            "PostCode_Physical": null,
            "SameAddress": true,
            "SameAddress1": null,
            "SingleLine_Physical": "  , null null null null,  null null",
            "State_Physical": null,
            "StreetName_Physical": null,
            "StreetName_Physical_UPPER": "",
            "StreetNumber_Physical": null,
            "StreetNumber_Physical_UPPER": "",
            "StreetSuffix_Physical": null,
            "StreetType_Physical": null,
            "SuburbOrTown_Physical": null,
            "SuburbOrTown_Physical_UPPER": "",
            "UnitRadio_Physical": null,
            "Unit_Physical": null,
            "Unit_Physical_UPPER": "",
            "ValidatePhysicalAddress": "GOOD"
        },
        "Messaging4": null,
        "Messaging8": null
    },
    "Physical_Candidates": {
        "AddressRecordType": "Physical Address",
        "CurrentRecordId": null,
        "LocationId": null,
        "LocationRecordType": "Account Address",
        "OriginalInput": "dHA9MCNsb2M9NzE0NjgwI2xuZz0wI2xicz0xMDk6NDg4OTkxNTc=",
        "OriginalInputSingleLine": "",
        "ValidAddress": "Valid",
        "add_bldg": "",
        "add_num": "",
        "add_num_from": "",
        "add_num_to": "",
        "add_range": "",
        "addr_type": "StreetName",
        "bldg_name": "",
        "bldg_type": "",
        "block": "",
        "city": "",
        "country": "",
        "display_latitude": -28.75805100062475,
        "display_longitude": 136.87591950015707,
        "distance": 0,
        "district": "",
        "ex_info": "",
        "federal_electorate": "GREY",
        "full_address": "TEST LAKE EYRE SA",
        "gnaf_pid": "SA3616123",
        "lang_code": "ENG",
        "latitude": -28.75805100062475,
        "latitude_max": -28.757051000625644,
        "latitude_min": -28.759051000623877,
        "leagal_parcel_id": "",
        "level_name": "",
        "level_type": "",
        "lga": "",
        "long_label": "TEST, LAKE EYRE, SA",
        "longitude": 136.87591950015707,
        "longitude_max": 136.87691950015622,
        "longitude_min": 136.87491950015786,
        "match_addr": "TEST, LAKE EYRE, SA",
        "meshblock": "",
        "metro_area": "",
        "nbrhd": "LAKE EYRE",
        "phone": "",
        "place_addr": "TEST, LAKE EYRE, SA",
        "place_name": "",
        "postal": "",
        "postal_ext": "",
        "rank": 20,
        "region": "SA",
        "region_abbr": "SA",
        "sa1": 0,
        "score": 100,
        "sector": "",
        "short_label": "TEST",
        "side": "",
        "st_addr": "TEST",
        "st_dir": "",
        "st_name": "TEST",
        "st_pre_dir": "",
        "st_pre_type": "",
        "st_type": "",
        "state_electorate": "",
        "status": "M",
        "sub_addr": "",
        "sub_region": "",
        "success": "OK",
        "territory": "",
        "type": "",
        "unit_name": "",
        "unit_type": "",
        "url": "",
        "zone": ""
    },
    "PostalAddresses": null,
    "Postal_Candidates": null,
    "RecordType": "Management Company",
    "SDOABNDuplicateCheckError": "Ok",
    "SearchMC": {
        "FindMC": {
            "ChooseMC": "Create a new Management Company",
            "MCInformation-Block": null
        }
    },
    "SelectPhysicalAddress": null,
    "SelectPostalAddress": null,
    "Selection": "Both Addresses",
    "SelectionForm": null,
    "SelectionOverride": "Both Addresses",
    "ShowEffectiveDate": "Yes",
    "ShowEffectiveDateOverride": "Yes",
    "SummaryPage": {
        "ABNBranch": "001",
        "ABNEntityName": "NORLEX PTY. LTD.",
        "ABNEntityNameEffectiveFrom": "8/4/2004",
        "ABNEntityNameEffectiveTo": "",
        "ABNEntityType": "Australian Private Company",
        "ABNLastUpdated": "22/4/2015",
        "ABNNumber": "14074218956",
        "ABNStatus": "Cancelled",
        "ABNStatusEffectiveFrom": "30/6/2008",
        "ABNStatusEffectiveTo": "",
        "ACNCRegistrationStatus": "",
        "ACNCRegistrationStatusEffectiveFrom": "",
        "ACNCRegistrationStatusEffectiveTo": "",
        "ACOId": "NotApplicable",
        "ACO_ARBN": "",
        "ACO_IncorporatedUnder": "",
        "ACO_IncorporationID": "",
        "ACO_IncorporationIDType": "",
        "ACO_IncorporationStatus": "",
        "ACO_IncorporationStatusDate": "",
        "ACO_IncorporationType": "",
        "ACO_Name": "",
        "ACO_RegisAddress": "NotApplicable",
        "ACO_RegisAddressCareOf": "",
        "ASICNumber": "074218956",
        "BranchOrDepartmentName": "",
        "Email": "tettttt@tetstt.com",
        "Fax": "",
        "GREFlag": "N",
        "KPId": "",
        "KP_EffectOnSuitability": "",
        "KP_Email": "",
        "KP_Employer": "",
        "KP_Employer_AO": "",
        "KP_Employer_AP": "",
        "KP_Employer_MC": "",
        "KP_Employer_SDO": "",
        "KP_EmploymentEndDate": "",
        "KP_EmploymentStartDate": "",
        "KP_EmploymentType": "",
        "KP_EndDate_KP": "",
        "KP_FirstName": "",
        "KP_LastName": "",
        "KP_MiddleName": "",
        "KP_Mobile": "",
        "KP_Phone": "",
        "KP_PositionTitle": "",
        "KP_ReasonForDeparture": "",
        "KP_Role": "",
        "KP_StartDate": "",
        "LastABRRefreshDate": "8/12/2022",
        "MCId": "NotApplicable",
        "MC_ID": "NotApplicable",
        "MC_Name": "test abnid",
        "MC_NameEffectiveDate": "2022-12-08",
        "POCId": "0039r000001k5CEAAY",
        "POC_Email": "",
        "POC_EndDate": "",
        "POC_FirstName": "Sarah",
        "POC_LastName": "SDO KP (workflow test)",
        "POC_MiddleName": "",
        "POC_Mobile": "",
        "POC_Phone": "0455335555",
        "POC_PositionTitle": "tytutyu",
        "POC_Role": "Service Contact",
        "POC_StartDate": "2022-12-05T13:00:00.000Z",
        "Phone": "0455336666",
        "PhysAddress_FullAddress": "TEST, LAKE EYRE, SA",
        "PostAddress_FullAddress": "TEST, LAKE EYRE, SA",
        "PostalAddress_CareOf": "",
        "PostalAddress_POBox": "NotApplicable",
        "RegisteredforGST": "No",
        "ValidatedABN": "NotApplicable",
        "Website": ""
    },
    "ValidateContactName": "Sarah SDO KP (workflow test)",
    "ValidatedContactDriverLicenceNumber": "No",
    "ValidatedContactId": "0039r000001k5CEAAY",
    "ValidatedContactPassportNumber": "3097",
    "ValidatedExistingPOC": "Ok",
    "data": {
        "GREFlag": "N",
        "abnChanged": false,
        "businessEntity202001_abn_identifier_value": "14074218956",
        "businessEntity202001_abn_is_current_indicator": "Y",
        "businessEntity202001_abn_replaced_from": "0001-01-01",
        "businessEntity202001_asic_number": "074218956",
        "businessEntity202001_entity_status_effective_from": "30/6/2008",
        "businessEntity202001_entity_status_effective_from_Load": "2008-06-30",
        "businessEntity202001_entity_status_effective_to": "1/1/0001",
        "businessEntity202001_entity_status_effective_to_Load": "0001-01-01",
        "businessEntity202001_entity_status_entity_status_code": "Cancelled",
        "businessEntity202001_entity_type_entity_description": "Australian Private Company",
        "businessEntity202001_entity_type_entity_type_code": "PRV",
        "businessEntity202001_main_business_physical_address_effective_from": "2007-04-19",
        "businessEntity202001_main_business_physical_address_effective_to": "0001-01-01",
        "businessEntity202001_main_business_physical_address_post_code": "4501",
        "businessEntity202001_main_business_physical_address_state_code": "QLD",
        "businessEntity202001_main_name_effective_from": "8/4/2004",
        "businessEntity202001_main_name_effective_from_Load": "2004-04-08",
        "businessEntity202001_main_name_organisation_name": "NORLEX PTY. LTD.",
        "businessEntity202001_record_last_updated_date": "22/4/2015",
        "businessEntity202001_record_last_updated_date_Load": "2015-04-22",
        "currentABNChanged": false,
        "date_register_last_updated": "8/12/2022",
        "date_time_retrieved": "8/12/2022",
        "date_time_retrieved_Load": "2022-12-08",
        "registeredforGST": "No",
        "usage_statement": "The Registrar of the ABR monitors the quality of the information available on this website and updates the information regularly. However, neither the Registrar of the ABR nor the Commonwealth guarantee that the information available through this service (including search results) is accurate, up to date, complete or accept any liability arising from the use of or reliance upon this site."
    },
    "success": "OK",
    "timeStamp": "2022-12-08T00:16:57.818Z",
    "userCurrencyCode": "AUD",
    "userId": "0059r000001a9QnAAI",
    "userName": "lavanya.uddarraju@health.gov.au.dohsit1.prvddev",
    "userProfile": "System Administrator",
    "userTimeZone": "660",
    "userTimeZoneName": "Australia/Sydney"
}