{
    "DiscoveryFrameworkUsageType": "Default",
    "IsActive": true,
    "IsOmniScriptEmbeddable": false,
    "Name": "SetDiscontinuingServiceId",
    "OmniProcessId": {
        "Name": "ServiceCombine",
        "VlocityDataPackType": "VlocityMatchingKeyObject",
        "VlocityMatchingRecordSourceKey": "OmniProcess/ServiceCombine/Create/English",
        "VlocityRecordSObjectType": "OmniProcess"
    },
    "PropertySetConfig": {
        "HTMLTemplateId": "",
        "controlWidth": 12,
        "elementValueMap": {
            "DiscontinuingServiceId": "=%SelectDiscontinuingService:Discontinuing:DiscontinuingService:DiscontinuingService:Id%"
        },
        "label": "SetDiscontinuingServiceId",
        "message": {
        },
        "pubsub": false,
        "show": null,
        "showPersistentComponent": [
            true,
            false
        ],
        "ssm": false,
        "wpm": false
    },
    "Type": "Set Values",
    "VlocityDataPackType": "SObject",
    "VlocityRecordSObjectType": "OmniProcessElement",
    "VlocityRecordSourceKey": "OmniProcessElement/OmniProcess/ServiceCombine/Create/English/SetDiscontinuingServiceId"
}