{
    "AllotmentId": "{AllotmentId}",
    "CorrectAction": "",
    "CorrectPA": null,
    "EventId": "a2Z9r0000001pA9EAI",
    "EventId1": "a2Z9r0000001pA9EAI",
    "EventStatus": "Not Approved: Under AAT Reconsideration",
    "EventStatus1": "Not Approved: Under AAT Reconsideration",
    "ExpectedExtendedPAPeriodEndDate": "2023-12-08",
    "ExtractPA": {
        "Comments": "cghjmdgjfg",
        "Comments2": null,
        "DateofRequest": null,
        "Decision2": null,
        "Decision3": "Uphold Decision",
        "DecisionDate": null,
        "DecisionDate1": null,
        "DecisionDate2": null,
        "DecisionDate5": "2023-01-07",
        "DecisionDueDate": "NaN/NaN/NaN",
        "DecisionDueDate1": null,
        "DecisionDueDateLoad": "NaN-NaN-NaN",
        "DecisionDueDateValidFormula": "BAD",
        "DelegateName": null,
        "DelegatePosition": null,
        "IsActing": null,
        "LinktoDocument": "dfgnrh",
        "Messaging1": null,
        "Messaging2": null,
        "Messaging3": null,
        "PreviousDateOfRequest": null,
        "PreviousDateOfRequestATT": null,
        "PreviousDateOfRequestValidation": "BAD",
        "PreviousDateOfRequestValidationATT": "BAD",
        "RequestType": null
    },
    "GPMSExtendPAPeriodDetailsCount": "",
    "ObjectTypeForEventValidation": "Allotment__c",
    "PerformAction": {
        "Action": "Record AAT Decision",
        "Select1": null,
        "Select2": null,
        "Select3": null,
        "Select4": "Record AAT Decision",
        "Select5": null,
        "Selection1": null,
        "Selection2": null,
        "Selection3": null,
        "Selection4": null,
        "Selection5": "Select Next Action"
    },
    "ProvisionalPlacesNumber": "0",
    "SizeOfCurrentProvisional": 0,
    "timeStamp": "2022-12-06T20:35:30.895Z",
    "userCurrencyCode": "AUD",
    "userId": "0059r000000ylz1AAA",
    "userName": "scott.naughton@health.gov.au.prvddev",
    "userProfile": "Project Administrator",
    "userTimeZone": "660",
    "userTimeZoneName": "Australia/Sydney"
}