{
    "IsActive": true,
    "IsOmniScriptEmbeddable": false,
    "Name": "OnlyifWeNeedToCreateTheInContextAccountRecord",
    "OmniProcessId": {
        "Name": "CreateServiceDeliveryOrganisation",
        "VlocityDataPackType": "VlocityMatchingKeyObject",
        "VlocityMatchingRecordSourceKey": "OmniProcess/ServiceDeliveryOrganisation/Create/Procedure",
        "VlocityRecordSObjectType": "OmniProcess"
    },
    "PropertySetConfig": {
        "disOnTplt": false,
        "executionConditionalFormula": "SearchSDO:FindSDO:ChooseSDO == \"Create a new Service Delivery Organisation\"",
        "isIfElseBlock": false,
        "label": "ConditionalBlock5",
        "show": null
    },
    "Type": "Conditional Block",
    "VlocityDataPackType": "SObject",
    "VlocityRecordSObjectType": "OmniProcessElement",
    "VlocityRecordSourceKey": "OmniProcessElement/OmniProcess/ServiceDeliveryOrganisation/Create/Procedure/OnlyifWeNeedToCreateTheInContextAccountRecord"
}