{
    "DiscoveryFrameworkUsageType": "Default",
    "IsActive": true,
    "IsOmniScriptEmbeddable": false,
    "Name": "QIForAllServs",
    "OmniProcessId": {
        "Name": "QIRatingCalculation",
        "VlocityDataPackType": "VlocityMatchingKeyObject",
        "VlocityMatchingRecordSourceKey": "OmniProcess/SRQI/QIRatingCalculation/Procedure",
        "VlocityRecordSObjectType": "OmniProcess"
    },
    "PropertySetConfig": {
        "disOnTplt": false,
        "executionConditionalFormula": "(ServID == null && lateUpdate == null) OR runAll == 'true'",
        "isIfElseBlock": false,
        "label": "ConditionalBlock1",
        "show": null
    },
    "Type": "Conditional Block",
    "VlocityDataPackType": "SObject",
    "VlocityRecordSObjectType": "OmniProcessElement",
    "VlocityRecordSourceKey": "OmniProcessElement/OmniProcess/SRQI/QIRatingCalculation/Procedure/QIForAllServs"
}