{
    "DiscoveryFrameworkUsageType": "Default",
    "IsActive": true,
    "IsOmniScriptEmbeddable": false,
    "Name": "VariationAction",
    "OmniProcessId": {
        "Name": "Variation",
        "VlocityDataPackType": "VlocityMatchingKeyObject",
        "VlocityMatchingRecordSourceKey": "OmniProcess/Variation/Create/Procedure",
        "VlocityRecordSObjectType": "OmniProcess"
    },
    "PropertySetConfig": {
        "disOnTplt": false,
        "executionConditionalFormula": "%EventId% != NULL && %Type% != \"New\"",
        "isIfElseBlock": false,
        "label": "ConditionalBlock17",
        "show": null
    },
    "Type": "Conditional Block",
    "VlocityDataPackType": "SObject",
    "VlocityRecordSObjectType": "OmniProcessElement",
    "VlocityRecordSourceKey": "OmniProcessElement/OmniProcess/Variation/Create/Procedure/VariationAction"
}