{
    "IsActive": true,
    "IsOmniScriptEmbeddable": false,
    "Name": "ResponseAction",
    "OmniProcessId": {
        "Name": "CeasePA",
        "VlocityDataPackType": "VlocityMatchingKeyObject",
        "VlocityMatchingRecordSourceKey": "OmniProcess/CeasePA/Create/Procedure",
        "VlocityRecordSObjectType": "OmniProcess"
    },
    "PropertySetConfig": {
        "additionalOutput": {
            "EventId": "=%EventId%",
            "PlacesAllotmentId": "=%PlacesAllotmentId%"
        },
        "disOnTplt": false,
        "executionConditionalFormula": "",
        "label": "ResponseAction1",
        "responseDefaultData": {
        },
        "responseFormat": "JSON",
        "responseJSONNode": "",
        "responseJSONPath": "",
        "returnFullDataJSON": false,
        "returnOnlyAdditionalOutput": false,
        "sendJSONNode": "",
        "sendJSONPath": "",
        "show": null,
        "useFormulas": true,
        "vlcResponseHeaders": {
        }
    },
    "Type": "Response Action",
    "VlocityDataPackType": "SObject",
    "VlocityRecordSObjectType": "OmniProcessElement",
    "VlocityRecordSourceKey": "OmniProcessElement/OmniProcess/CeasePA/Create/Procedure/ResponseAction"
}