{
    "Activate": {
    },
    "Cancel": {
    },
    "ChangeVariationDay": {
    },
    "ContextId": null,
    "CreateServiceChangeEvent_ResidentialOnly": {
    },
    "GetAllAssociatedAllotments": {
    },
    "RecordADecisionOnRequestForReconsideration": {
    },
    "RecordDecision": {
    },
    "RecordRequestforReconsideration": {
    },
    "Withdraw": {
    },
    "timeStamp": null,
    "userId": null,
    "userName": null,
    "userProfile": null,
    "userTimeZone": null,
    "vlcPersistentComponent": {
    },
    "vlcTimeTracking": {
        "Activate": null,
        "Cancel": null,
        "ChangeVariationDay": null,
        "CreateServiceChangeEvent_ResidentialOnly": null,
        "GetAllAssociatedAllotments": null,
        "RecordADecisionOnRequestForReconsideration": null,
        "RecordDecision": null,
        "RecordRequestforReconsideration": null,
        "ResponseAction": null,
        "Withdraw": null
    }
}