{
    "DiscoveryFrameworkUsageType": "Default",
    "IsActive": true,
    "IsOmniScriptEmbeddable": false,
    "Name": "Allotment_ExtractAll",
    "OmniProcessId": {
        "Name": "PAVariation",
        "VlocityDataPackType": "VlocityMatchingKeyObject",
        "VlocityMatchingRecordSourceKey": "OmniProcess/PAVariation/Create/Procedure",
        "VlocityRecordSObjectType": "OmniProcess"
    },
    "ParentElementId": {
        "Name": "NoServiceNoCareLevel",
        "OmniProcessId": {
            "Name": "PAVariation",
            "VlocityDataPackType": "VlocityMatchingKeyObject",
            "VlocityMatchingRecordSourceKey": "OmniProcess/PAVariation/Create/Procedure",
            "VlocityRecordSObjectType": "OmniProcess"
        },
        "VlocityDataPackType": "VlocityMatchingKeyObject",
        "VlocityMatchingRecordSourceKey": "OmniProcessElement/OmniProcess/PAVariation/Create/Procedure/NoServiceNoCareLevel",
        "VlocityRecordSObjectType": "OmniProcessElement"
    },
    "ParentElementName": "NoServiceNoCareLevel",
    "ParentElementType": "Conditional Block",
    "PropertySetConfig": {
        "actionMessage": "",
        "additionalInput": {
            "AllotmentId": "=%AllotmentId%"
        },
        "additionalOutput": {
        },
        "bundle": "Allotment_Extract",
        "chainOnStep": false,
        "dataRaptor Input Parameters": [
        ],
        "disOnTplt": false,
        "executionConditionalFormula": "",
        "failOnStepError": true,
        "failureConditionalFormula": "",
        "failureResponse": {
        },
        "ignoreCache": false,
        "label": "DataRaptorExtractAction3",
        "responseJSONNode": "Provisional",
        "responseJSONPath": "Provisional",
        "returnOnlyAdditionalOutput": false,
        "returnOnlyFailureResponse": false,
        "sendJSONNode": "",
        "sendJSONPath": "",
        "sendOnlyAdditionalInput": true,
        "show": null,
        "useFormulas": true
    },
    "Type": "DataRaptor Extract Action",
    "VlocityDataPackType": "SObject",
    "VlocityRecordSObjectType": "OmniProcessElement",
    "VlocityRecordSourceKey": "OmniProcessElement/OmniProcess/PAVariation/Create/Procedure/Allotment_ExtractAll"
}