{
    "IsActive": true,
    "IsOmniScriptEmbeddable": false,
    "Name": "TextBlock3",
    "OmniProcessId": {
        "Name": "PlacesTransfer",
        "VlocityDataPackType": "VlocityMatchingKeyObject",
        "VlocityMatchingRecordSourceKey": "OmniProcess/Places/Transfer/English",
        "VlocityRecordSObjectType": "OmniProcess"
    },
    "ParentElementId": {
        "Name": "Transfer",
        "OmniProcessId": {
            "Name": "PlacesTransfer",
            "VlocityDataPackType": "VlocityMatchingKeyObject",
            "VlocityMatchingRecordSourceKey": "OmniProcess/Places/Transfer/English",
            "VlocityRecordSObjectType": "OmniProcess"
        },
        "VlocityDataPackType": "VlocityMatchingKeyObject",
        "VlocityMatchingRecordSourceKey": "OmniProcessElement/OmniProcess/Places/Transfer/English/Transfer",
        "VlocityRecordSObjectType": "OmniProcessElement"
    },
    "ParentElementName": "Transfer",
    "ParentElementType": "Step",
    "PropertySetConfig": {
        "HTMLTemplateId": "",
        "controlWidth": 12,
        "dataJSON": false,
        "label": "TextBlock3",
        "sanitize": false,
        "show": null,
        "text": "<h2>%PerformAction:Action%</h2>",
        "textKey": ""
    },
    "Type": "Text Block",
    "VlocityDataPackType": "SObject",
    "VlocityRecordSObjectType": "OmniProcessElement",
    "VlocityRecordSourceKey": "OmniProcessElement/OmniProcess/Places/Transfer/English/TextBlock3"
}