{
    "AllotmentId": "a2U9r0000000YRVEA2",
    "CurrentProvisional": [
        {
            "CareLevel": "Residential",
            "CareSetting": "Residential",
            "CareSettingEffectiveDate": "2022-11-02",
            "CareType": "Residential",
            "Current": "Yes",
            "FirstBroughtIntoEffectDate": "2022-10-30",
            "Id": "a2a9r000000Esa1AAC",
            "Name": "PALT-000106",
            "NumberOfPlaces": 20,
            "StatusEffectiveDate": "2022-10-30",
            "StatusOfPlaces": "Provisional",
            "StatusReason": "S15-1 Determined to be in effect at time of allocation (Operational)"
        },
        {
            "CareLevel": "Residential",
            "CareSetting": "Residential",
            "CareSettingEffectiveDate": "2022-11-01",
            "CareType": "Residential",
            "Current": "Yes",
            "FirstBroughtIntoEffectDate": "2022-11-02",
            "Id": "a2a9r000000F2mIAAS",
            "Name": "PALT-000448",
            "NumberOfPlaces": 20,
            "StatusEffectiveDate": "2022-11-01",
            "StatusOfPlaces": "Provisional",
            "StatusReason": "S15-1 Provisional allocation (Provisional)"
        },
        {
            "CareLevel": "Residential",
            "CareSetting": "Residential",
            "CareSettingEffectiveDate": "2022-11-02",
            "CareType": "Residential",
            "Current": "Yes",
            "FirstBroughtIntoEffectDate": "2022-11-04",
            "Id": "a2a9r000000F2skAAC",
            "Name": "PALT-000453",
            "NumberOfPlaces": 15,
            "StatusEffectiveDate": "2022-11-03",
            "StatusOfPlaces": "Provisional",
            "StatusReason": "S15-1 Provisional allocation (Provisional)"
        },
        {
            "CareLevel": "Residential",
            "CareSetting": "Residential",
            "CareSettingEffectiveDate": "2022-11-02",
            "CareType": "Residential",
            "Current": "Yes",
            "FirstBroughtIntoEffectDate": "2022-11-09",
            "Id": "a2a9r000000F3NOAA0",
            "Name": "PALT-000457",
            "NumberOfPlaces": 15,
            "StatusEffectiveDate": "2022-11-02",
            "StatusOfPlaces": "Provisional",
            "StatusReason": "S15-1 Provisional allocation (Provisional)"
        },
        {
            "CareLevel": "Residential",
            "CareSetting": "Residential",
            "CareSettingEffectiveDate": "2022-11-02",
            "CareType": "Residential",
            "Current": "Yes",
            "FirstBroughtIntoEffectDate": "2022-10-30",
            "Id": "a2a9r000000F5AfAAK",
            "Name": "PALT-000549",
            "NumberOfPlaces": 20,
            "StatusEffectiveDate": "2022-10-30",
            "StatusOfPlaces": "Provisional",
            "StatusReason": "S15-1 Determined to be in effect at time of allocation (Operational)"
        }
    ],
    "DateOfAllotment": "2022-11-10",
    "Error": null,
    "EventType": "Surrender PA",
    "Location": "300 Bendigo Street",
    "NotificationOfSurrenderDetails": {
        "DateOfAllotmentValidationFormula": "GOOD",
        "LinkToDocuments": null,
        "Messaging1": null,
        "Messaging2": true,
        "NotificationReceivedDate": "2022-11-22",
        "PAPeriodEndDateValidationFormula": "GOOD",
        "SurrenderEffectiveDate": "2022-12-01"
    },
    "PAPeriodEndDate": "2022-12-20",
    "ProvisionalPlacesNumber": 3,
    "ServiceId": "0cE9r0000003TGnEAM",
    "ServiceName": "Dale Service",
    "addressLocationCheck": null,
    "eventStatusCheck": null,
    "timeStamp": "2022-11-22T02:58:38.130Z",
    "userCurrencyCode": "AUD",
    "userId": "0059r0000021EJ7AAM",
    "userName": "dalin.wang@health.gov.au.prvddev",
    "userProfile": "Project Administrator",
    "userTimeZone": "660",
    "userTimeZoneName": "Australia/Sydney"
}