{
    "DiscoveryFrameworkUsageType": "Default",
    "IsActive": true,
    "IsOmniScriptEmbeddable": false,
    "Name": "LoopBlock1",
    "OmniProcessId": {
        "Name": "CalculateCERData",
        "VlocityDataPackType": "VlocityMatchingKeyObject",
        "VlocityMatchingRecordSourceKey": "OmniProcess/CER/CER/Procedure",
        "VlocityRecordSObjectType": "OmniProcess"
    },
    "ParentElementId": {
        "Name": "Condition_ConsentProvided",
        "OmniProcessId": {
            "Name": "CalculateCERData",
            "VlocityDataPackType": "VlocityMatchingKeyObject",
            "VlocityMatchingRecordSourceKey": "OmniProcess/CER/CER/Procedure",
            "VlocityRecordSObjectType": "OmniProcess"
        },
        "VlocityDataPackType": "VlocityMatchingKeyObject",
        "VlocityMatchingRecordSourceKey": "OmniProcessElement/OmniProcess/CER/CER/Procedure/Condition_ConsentProvided",
        "VlocityRecordSObjectType": "OmniProcessElement"
    },
    "ParentElementName": "Condition_ConsentProvided",
    "ParentElementType": "Conditional Block",
    "PropertySetConfig": {
        "disOnTplt": false,
        "executionConditionalFormula": "",
        "label": "LoopBlock1",
        "loopList": "AnswerList",
        "loopOutput": {
            "DomainPercentages": "%MultiplyforPercent%",
            "DomainRatings": "%CalcDomainRatings:output:calculationResults%",
            "DomainScores": "%CalcDomainScores:output:calculationResults%"
        },
        "show": null
    },
    "Type": "Loop Block",
    "VlocityDataPackType": "SObject",
    "VlocityRecordSObjectType": "OmniProcessElement",
    "VlocityRecordSourceKey": "OmniProcessElement/OmniProcess/CER/CER/Procedure/LoopBlock1"
}