{
    "IsActive": true,
    "IsOmniScriptEmbeddable": false,
    "Name": "ResponseAction1",
    "OmniProcessId": {
        "Name": "SRQI_IP_SaveRegulatoryDecision",
        "VlocityDataPackType": "VlocityMatchingKeyObject",
        "VlocityMatchingRecordSourceKey": "OmniProcess/SRQI/SaveRegulatoryDecision/Procedure",
        "VlocityRecordSObjectType": "OmniProcess"
    },
    "PropertySetConfig": {
        "additionalOutput": {
        },
        "disOnTplt": false,
        "executionConditionalFormula": "",
        "label": "ResponseAction1",
        "responseDefaultData": {
        },
        "responseFormat": "JSON",
        "responseJSONNode": "",
        "responseJSONPath": "",
        "returnFullDataJSON": false,
        "returnOnlyAdditionalOutput": false,
        "sendJSONNode": "",
        "sendJSONPath": "DRSaveRegulatoryDecision:RegulatoryCodeViolation_1",
        "show": null,
        "useFormulas": true,
        "vlcResponseHeaders": {
        }
    },
    "Type": "Response Action",
    "VlocityDataPackType": "SObject",
    "VlocityRecordSObjectType": "OmniProcessElement",
    "VlocityRecordSourceKey": "OmniProcessElement/OmniProcess/SRQI/SaveRegulatoryDecision/Procedure/ResponseAction1"
}