{
    "DiscoveryFrameworkUsageType": "Default",
    "IsActive": false,
    "IsOmniScriptEmbeddable": false,
    "Name": "ServiceCombinePost",
    "OmniProcessId": {
        "Name": "ServiceCombine",
        "VlocityDataPackType": "VlocityMatchingKeyObject",
        "VlocityMatchingRecordSourceKey": "OmniProcess/ServiceCombine/ServiceCombine/Procedure",
        "VlocityRecordSObjectType": "OmniProcess"
    },
    "ParentElementId": {
        "Name": "ServiceCombineEvent",
        "OmniProcessId": {
            "Name": "ServiceCombine",
            "VlocityDataPackType": "VlocityMatchingKeyObject",
            "VlocityMatchingRecordSourceKey": "OmniProcess/ServiceCombine/ServiceCombine/Procedure",
            "VlocityRecordSObjectType": "OmniProcess"
        },
        "VlocityDataPackType": "VlocityMatchingKeyObject",
        "VlocityMatchingRecordSourceKey": "OmniProcessElement/OmniProcess/ServiceCombine/ServiceCombine/Procedure/ServiceCombineEvent",
        "VlocityRecordSObjectType": "OmniProcessElement"
    },
    "ParentElementName": "ServiceCombineEvent",
    "ParentElementType": "Conditional Block",
    "PropertySetConfig": {
        "actionMessage": "",
        "additionalInput": {
            "ServiceId": "=%ServiceId%"
        },
        "additionalOutput": {
        },
        "bundle": "ServiceCreation_Post",
        "chainOnStep": false,
        "disOnTplt": false,
        "executionConditionalFormula": "",
        "failOnStepError": true,
        "failureConditionalFormula": "",
        "failureResponse": {
        },
        "label": "DataRaptorPostAction11",
        "responseJSONNode": "ServiceId",
        "responseJSONPath": "BusinessLicense_1:Id",
        "returnOnlyAdditionalOutput": false,
        "returnOnlyFailureResponse": false,
        "sendJSONNode": "",
        "sendJSONPath": "",
        "sendOnlyAdditionalInput": false,
        "show": null,
        "useFormulas": true
    },
    "Type": "DataRaptor Post Action",
    "VlocityDataPackType": "SObject",
    "VlocityRecordSObjectType": "OmniProcessElement",
    "VlocityRecordSourceKey": "OmniProcessElement/OmniProcess/ServiceCombine/ServiceCombine/Procedure/ServiceCombinePost"
}