[
    {
        "GlobalKey": "FlexibleServiceCreation_PostCustom0jI9r000000088rEAAItem2",
        "InputFieldName": "NoFlexibleCare",
        "IsDisabled": false,
        "IsRequiredForUpsert": false,
        "IsUpsertKey": false,
        "Name": "FlexibleServiceCreation_Post",
        "OmniDataTransformationId": {
            "Name": "FlexibleServiceCreation_Post",
            "VlocityDataPackType": "VlocityMatchingKeyObject",
            "VlocityMatchingRecordSourceKey": "OmniDataTransform/FlexibleServiceCreation_Post",
            "VlocityRecordSObjectType": "OmniDataTransform"
        },
        "OutputCreationSequence": 1,
        "OutputFieldName": "Care_Type__c",
        "OutputObjectName": "BusinessLicense",
        "VlocityDataPackType": "SObject",
        "VlocityRecordSObjectType": "OmniDataTransformItem"
    },
    {
        "GlobalKey": "FlexibleServiceCreation_PostCustom0jI9r000000088rEAAItem3",
        "InputFieldName": "OnlyHomeCare",
        "IsDisabled": false,
        "IsRequiredForUpsert": false,
        "IsUpsertKey": false,
        "Name": "FlexibleServiceCreation_Post",
        "OmniDataTransformationId": {
            "Name": "FlexibleServiceCreation_Post",
            "VlocityDataPackType": "VlocityMatchingKeyObject",
            "VlocityMatchingRecordSourceKey": "OmniDataTransform/FlexibleServiceCreation_Post",
            "VlocityRecordSObjectType": "OmniDataTransform"
        },
        "OutputCreationSequence": 1,
        "OutputFieldName": "Care_Type__c",
        "OutputObjectName": "BusinessLicense",
        "VlocityDataPackType": "SObject",
        "VlocityRecordSObjectType": "OmniDataTransformItem"
    },
    {
        "FilterOperator": "=",
        "GlobalKey": "FlexibleServiceCreation_PostCustom0jI9r000000088rEAAItem0",
        "IsDisabled": true,
        "IsRequiredForUpsert": false,
        "IsUpsertKey": false,
        "MigrationValue": "FAKEMAPPING",
        "Name": "FlexibleServiceCreation_Post",
        "OmniDataTransformationId": {
            "Name": "FlexibleServiceCreation_Post",
            "VlocityDataPackType": "VlocityMatchingKeyObject",
            "VlocityMatchingRecordSourceKey": "OmniDataTransform/FlexibleServiceCreation_Post",
            "VlocityRecordSObjectType": "OmniDataTransform"
        },
        "OutputCreationSequence": 1,
        "OutputFieldName": "Id",
        "OutputObjectName": "BusinessLicense",
        "VlocityDataPackType": "SObject",
        "VlocityRecordSObjectType": "OmniDataTransformItem"
    },
    {
        "GlobalKey": "FlexibleServiceCreation_PostCustom0jI9r000000088rEAAItem1",
        "InputFieldName": "Service_Name",
        "IsDisabled": false,
        "IsRequiredForUpsert": false,
        "IsUpsertKey": false,
        "Name": "FlexibleServiceCreation_Post",
        "OmniDataTransformationId": {
            "Name": "FlexibleServiceCreation_Post",
            "VlocityDataPackType": "VlocityMatchingKeyObject",
            "VlocityMatchingRecordSourceKey": "OmniDataTransform/FlexibleServiceCreation_Post",
            "VlocityRecordSObjectType": "OmniDataTransform"
        },
        "OutputCreationSequence": 1,
        "OutputFieldName": "Name",
        "OutputObjectName": "BusinessLicense",
        "VlocityDataPackType": "SObject",
        "VlocityRecordSObjectType": "OmniDataTransformItem"
    }
]