{
    "DiscoveryFrameworkUsageType": "Default",
    "IsActive": true,
    "IsOmniScriptEmbeddable": true,
    "Name": "Block1",
    "OmniProcessId": {
        "Name": "MPSFoodandNutrition",
        "VlocityDataPackType": "VlocityMatchingKeyObject",
        "VlocityMatchingRecordSourceKey": "OmniProcess/ACFR/MPSFoodandNutrition/English",
        "VlocityRecordSObjectType": "OmniProcess"
    },
    "ParentElementId": {
        "Name": "MPSFoodandNutritionReporting",
        "OmniProcessId": {
            "Name": "MPSFoodandNutrition",
            "VlocityDataPackType": "VlocityMatchingKeyObject",
            "VlocityMatchingRecordSourceKey": "OmniProcess/ACFR/MPSFoodandNutrition/English",
            "VlocityRecordSObjectType": "OmniProcess"
        },
        "VlocityDataPackType": "VlocityMatchingKeyObject",
        "VlocityMatchingRecordSourceKey": "OmniProcessElement/OmniProcess/ACFR/MPSFoodandNutrition/English/MPSFoodandNutritionReporting",
        "VlocityRecordSObjectType": "OmniProcessElement"
    },
    "ParentElementName": "MPSFoodandNutritionReporting",
    "ParentElementType": "Step",
    "PropertySetConfig": {
        "HTMLTemplateId": "",
        "accessibleInFutureSteps": false,
        "collapse": false,
        "conditionType": "Hide if False",
        "controlWidth": 12,
        "hide": false,
        "label": "Reason(s) for reissuance of this form",
        "repeat": false,
        "repeatClone": false,
        "repeatLimit": null,
        "show": {
            "group": {
                "operator": "AND",
                "rules": [
                    {
                        "condition": "=",
                        "data": "true",
                        "field": "MPSFoodandNutrition_QAOutcome"
                    }
                ]
            }
        }
    },
    "Type": "Block",
    "VlocityDataPackType": "SObject",
    "VlocityRecordSObjectType": "OmniProcessElement",
    "VlocityRecordSourceKey": "OmniProcessElement/OmniProcess/ACFR/MPSFoodandNutrition/English/Block1"
}