{
    "DiscoveryFrameworkUsageType": "Default",
    "IsActive": false,
    "IsOmniScriptEmbeddable": false,
    "Name": "TESTValues",
    "OmniProcessId": {
        "Name": "PlacesEventsTransferCreate",
        "VlocityDataPackType": "VlocityMatchingKeyObject",
        "VlocityMatchingRecordSourceKey": "OmniProcess/PlacesEventsTransfer/Create/English",
        "VlocityRecordSObjectType": "OmniProcess"
    },
    "PropertySetConfig": {
        "HTMLTemplateId": "",
        "controlWidth": 12,
        "elementValueMap": {
            "FullAddress": "161 COLLINS STREET, MELBOURNE, VIC, 3000",
            "OpenTransferEvents": "4",
            "ProviderId": "001Bm000004Cb4lIAC",
            "ProviderIntegrationId": "PRV-12345678",
            "ProviderName": "Test Provider Dale",
            "ServiceCareType": "Residential",
            "ServiceId": "0cEBm00000007BBMAY",
            "ServiceIntegrationId": "SRV-15142",
            "ServiceName": "Niro Test Approved Provider Service"
        },
        "label": "TESTValues",
        "message": {
        },
        "pubsub": false,
        "show": null,
        "showPersistentComponent": [
            true,
            false
        ],
        "ssm": false,
        "wpm": false
    },
    "Type": "Set Values",
    "VlocityDataPackType": "SObject",
    "VlocityRecordSObjectType": "OmniProcessElement",
    "VlocityRecordSourceKey": "OmniProcessElement/OmniProcess/PlacesEventsTransfer/Create/English/TESTValues"
}