{
    "IsActive": true,
    "IsOmniScriptEmbeddable": false,
    "Name": "ifQI",
    "OmniProcessId": {
        "Name": "CreateServiceExemption",
        "VlocityDataPackType": "VlocityMatchingKeyObject",
        "VlocityMatchingRecordSourceKey": "OmniProcess/ServiceExemption/Create/Procedure",
        "VlocityRecordSObjectType": "OmniProcess"
    },
    "ParentElementId": {
        "Name": "ServiceExemptionFlags",
        "OmniProcessId": {
            "Name": "CreateServiceExemption",
            "VlocityDataPackType": "VlocityMatchingKeyObject",
            "VlocityMatchingRecordSourceKey": "OmniProcess/ServiceExemption/Create/Procedure",
            "VlocityRecordSObjectType": "OmniProcess"
        },
        "VlocityDataPackType": "VlocityMatchingKeyObject",
        "VlocityMatchingRecordSourceKey": "OmniProcessElement/OmniProcess/ServiceExemption/Create/Procedure/ServiceExemptionFlags",
        "VlocityRecordSObjectType": "OmniProcessElement"
    },
    "ParentElementName": "ServiceExemptionFlags",
    "ParentElementType": "Conditional Block",
    "PropertySetConfig": {
        "actionMessage": "",
        "chainOnStep": false,
        "disOnTplt": false,
        "elementValueMap": {
            "qiFlag": "=true"
        },
        "executionConditionalFormula": "Input:exemptionType == \"exemptQI\"",
        "failOnStepError": true,
        "failureConditionalFormula": "",
        "label": "SetValues2",
        "responseJSONNode": "qiFlag",
        "responseJSONPath": "qiFlag",
        "show": null
    },
    "Type": "Set Values",
    "VlocityDataPackType": "SObject",
    "VlocityRecordSObjectType": "OmniProcessElement",
    "VlocityRecordSourceKey": "OmniProcessElement/OmniProcess/ServiceExemption/Create/Procedure/ifQI"
}